{"cameraMode":{"drawMode":0,"name":"Shaded","section":"Shading Mode"},"sceneLighting":true,"audioPlay":false,"sceneViewState":{"m_AlwaysRefresh":false,"showFog":true,"showSkybox":true,"showFlares":true,"showImageEffects":true,"showParticleSystems":true,"showVisualEffectGraphs":true,"m_FxEnabled":true},"in2DMode":false,"pivot":{"x":0.8011938333511353,"y":1.3577841520309449,"z":4.976344585418701},"rotation":{"x":0.1584162712097168,"y":0.7215653657913208,"z":-0.17566803097724915,"w":0.6506982445716858},"size":3.9634997844696047,"orthographic":false}